ligavision/__version__.py
ligavision/spark/__init__.py
ligavision/spark/functions/__init__.py
ligavision/spark/functions/geometry.py
ligavision/spark/functions/io.py
ligavision/spark/functions/vision.py
ligavision/spark/types/__init__.py
ligavision/spark/types/geometry.py
ligavision/spark/types/video.py
ligavision/spark/types/vision.py
ligavision-0.3.0.dist-info/METADATA
ligavision-0.3.0.dist-info/WHEEL
ligavision-0.3.0.dist-info/namespace_packages.txt
ligavision-0.3.0.dist-info/top_level.txt
ligavision-0.3.0.dist-info/RECORD
